{"name":"DaosWelcome","number_of_posts_per_page":7,"disqus_shortname":"","posts":[{"title":"Data_Query_b","date":"2017-06-12","tags":"Data_Query","path":"Data_Query_b.html"},{"title":"Data_query_c","date":"2017-06-12","tags":"Data query","path":"Data_query_c.html","num":0,"type":"post","active":false},{"title":"Data_query_b","date":"2017-06-12","tags":"Data query","path":"Data_query_b.html","num":1,"type":"post","active":true},{"title":"Data_Query_a","date":"2017-06-12","tags":"Data_query","path":"Data_Query_a.html","num":2,"type":"post","active":false}],"pages":[]}